README.rst
setup.py
collective/__init__.py
collective.zoomit.egg-info/PKG-INFO
collective.zoomit.egg-info/SOURCES.txt
collective.zoomit.egg-info/dependency_links.txt
collective.zoomit.egg-info/entry_points.txt
collective.zoomit.egg-info/namespace_packages.txt
collective.zoomit.egg-info/not-zip-safe
collective.zoomit.egg-info/paster_plugins.txt
collective.zoomit.egg-info/requires.txt
collective.zoomit.egg-info/top_level.txt
collective/zoomit/__init__.py
collective/zoomit/behavior.py
collective/zoomit/config.py
collective/zoomit/configure.zcml
collective/zoomit/interfaces.py
collective/zoomit/tests.py
collective/zoomit/viewlet.py
collective/zoomit/behavior_templates/zoomitupdater.pt
collective/zoomit/locales/README.txt
collective/zoomit/profiles/default/actions.xml
collective/zoomit/profiles/default/jsregistry.xml
collective/zoomit/profiles/default/metadata.xml
collective/zoomit/resources/zoomit.js
docs/HISTORY.txt
docs/INSTALL.txt
docs/LICENSE.GPL
docs/LICENSE.txt