Metadata-Version: 1.1
Name: collective.zoomit
Version: 0.6
Summary: Integration of Zoom.it hosted image zoom in plone.
Home-page: http://svn.plone.org/svn/collective/
Author: Alec Mitchell, Jazkarta, Inc
Author-email: alecpm@gmail.com
License: GPL
Keywords: Deepzoom Zoom.it Images Plone
Platform: UNKNOWN
Classifier: Framework :: Plone
Classifier: Programming Language :: Python
Classifier: Topic :: Software Development :: Libraries :: Python Modules
